LICENSE
MANIFEST.in
README.md
setup.py
python_utilikilt.egg-info/PKG-INFO
python_utilikilt.egg-info/SOURCES.txt
python_utilikilt.egg-info/dependency_links.txt
python_utilikilt.egg-info/requires.txt
python_utilikilt.egg-info/top_level.txt
python_utils/__init__.py
python_utils/classes.py
python_utils/decorators.py
python_utils/iterators.py
python_utils/string.py