Metadata-Version: 1.0
Name: python-utilikilt
Version: 0.3b5
Summary: A collection of general python utility functions.
Home-page: https://bitbucket.org/nextscreenlabs/python-utils
Author: Jason Christa
Author-email: jason@zeitcode.com
License: UNKNOWN
Platform: UNKNOWN
Classifier: Environment :: Other Environment
Classifier: Intended Audience :: Developers
Classifier: License :: OSI Approved :: BSD License
Classifier: Programming Language :: Python
Classifier: Topic :: Utilities
